ntfy/__init__.py
ntfy/cli.py
ntfy/config.py
ntfy/data.py
ntfy/icon.ico
ntfy/icon.png
ntfy/terminal.py
ntfy/backends/__init__.py
ntfy/backends/darwin.py
ntfy/backends/default.py
ntfy/backends/insta.py
ntfy/backends/linux.py
ntfy/backends/matrix.py
ntfy/backends/notifico.py
ntfy/backends/prowl.py
ntfy/backends/pushalot.py
ntfy/backends/pushbullet.py
ntfy/backends/pushjet.py
ntfy/backends/pushover.py
ntfy/backends/rocketchat.py
ntfy/backends/simplepush.py
ntfy/backends/slack.py
ntfy/backends/systemlog.py
ntfy/backends/telegram.py
ntfy/backends/termux.py
ntfy/backends/win32.py
ntfy/backends/xmpp.py
ntfy/shell_integration/auto-ntfy-done.sh
ntfy/shell_integration/bash-preexec.sh
ntfy-2.7.0.dist-info/LICENSE
ntfy-2.7.0.dist-info/METADATA
ntfy-2.7.0.dist-info/WHEEL
ntfy-2.7.0.dist-info/entry_points.txt
ntfy-2.7.0.dist-info/top_level.txt
ntfy-2.7.0.dist-info/RECORD
