Metadata-Version: 2.1
Name: ntfy
Version: 2.7.0
Summary: A utility for sending push notifications
Home-page: https://github.com/dschep/ntfy
Author: Daniel Schep
Author-email: dschep@gmail.com
License: GPLv3
Keywords: push notification
Platform: UNKNOWN
Classifier: Development Status :: 5 - Production/Stable
Classifier: Environment :: Console
Classifier: Intended Audience :: End Users/Desktop
Classifier: License :: OSI Approved :: GNU General Public License v3 (GPLv3)
Classifier: Programming Language :: Python :: 2
Classifier: Programming Language :: Python :: 2.7
Classifier: Programming Language :: Python :: 3
Classifier: Programming Language :: Python :: 3.3
Classifier: Programming Language :: Python :: 3.4
Classifier: Programming Language :: Python :: 3.5
Classifier: Programming Language :: Python :: 3.6
Provides-Extra: slack
Provides-Extra: telegram
Provides-Extra: pid
Provides-Extra: xmpp
Provides-Extra: emoji
Provides-Extra: matrix
Provides-Extra: rocketchat
Provides-Extra: instapush
